{
    "version": "0.232.0",
    "description": "The Databricks command-line interface (also known as the Databricks CLI) provides a tool to automate the Databricks platform from your terminal, command prompt, or automation scripts.",
    "homepage": "https://github.com/databricks/cli",
    "license": {
        "identifier": "Databricks",
        "url": "https://raw.githubusercontent.com/databricks/cli/main/LICENSE"
    },
    "architecture": {
        "64bit": {
            "url": "https://github.com/databricks/cli/releases/download/v0.232.0/databricks_cli_0.232.0_windows_amd64.zip",
            "hash": "23d153c0b083eed379344e067ccaa12a5b2beff68b68864a55a48789eb00a176"
        }
    },
    "bin": "databricks.exe",
    "checkver": "github",
    "autoupdate": {
        "architecture": {
            "64bit": {
                "url": "https://github.com/databricks/cli/releases/download/v$version/databricks_cli_$version_windows_amd64.zip"
            }
        },
        "hash": {
            "url": "$baseurl/databricks_cli_$version_SHA256SUMS"
        }
    }
}
