{
    "version": "1.13.4",
    "description": "istioctl is a supplemental tool that provides debugging and diagnosis for Istio service mesh deployments.",
    "homepage": "https://istio.io/latest/docs/ops/diagnostic-tools/istioctl/",
    "license": "Apache-2.0",
    "architecture": {
        "64bit": {
            "url": "https://github.com/istio/istio/releases/download/1.13.4/istioctl-1.13.4-win.zip",
            "hash": "6390e839ef37d1208ecaa6f3e830a5af9d3ed4047aa176a6c5608e0c9cf8c86c"
        }
    },
    "bin": "istioctl.exe",
    "checkver": {
        "github": "https://github.com/istio/istio"
    },
    "autoupdate": {
        "architecture": {
            "64bit": {
                "url": "https://github.com/istio/istio/releases/download/$version/istioctl-$version-win.zip"
            }
        },
        "hash": {
            "url": "$url.sha256"
        }
    }
}
