{
    "version": "1.22.1",
    "description": "Bulk port forwarding Kubernetes services for local development",
    "homepage": "https://github.com/txn2/kubefwd",
    "license": "Apache-2.0",
    "architecture": {
        "64bit": {
            "url": "https://github.com/txn2/kubefwd/releases/download/1.22.1/kubefwd_Windows_x86_64.zip",
            "hash": "fa173c20d017e12ea34ac0044bfb0d79d07869d86efd64bb3e2ada0500f09151"
        },
        "32bit": {
            "url": "https://github.com/txn2/kubefwd/releases/download/1.22.1/kubefwd_Windows_i386.zip",
            "hash": "9a443225a8969f5705fdca327d27caa277d599645e81a8317ecc5da5c6af6cb6"
        }
    },
    "bin": "kubefwd.exe",
    "checkver": "github",
    "autoupdate": {
        "architecture": {
            "64bit": {
                "url": "https://github.com/txn2/kubefwd/releases/download/$version/kubefwd_Windows_x86_64.zip"
            },
            "32bit": {
                "url": "https://github.com/txn2/kubefwd/releases/download/$version/kubefwd_Windows_i386.zip"
            }
        },
        "hash": {
            "url": "$baseurl/kubefwd_checksums.txt"
        }
    }
}
