{
    "version": "6.2.0",
    "description": "A prompt theme engine for any shell",
    "homepage": "https://ohmyposh.dev",
    "license": "GPL-3.0-only",
    "notes": "Refer to 'https://ohmyposh.dev/docs/pwsh' for shell specific configurations.",
    "architecture": {
        "64bit": {
            "url": "https://github.com/JanDeDobbeleer/oh-my-posh/releases/download/v6.2.0/posh-windows-wsl-amd64.7z",
            "hash": "39fff05bd2d1eb78a5ff696b7b45ee65b9280ea30a69759b977dca2f2b4c5de9"
        }
    },
    "bin": "bin\\oh-my-posh.exe",
    "persist": "themes",
    "checkver": {
        "github": "https://github.com/JanDeDobbeleer/oh-my-posh"
    },
    "autoupdate": {
        "architecture": {
            "64bit": {
                "url": "https://github.com/JanDeDobbeleer/oh-my-posh/releases/download/v$version/posh-windows-wsl-amd64.7z"
            }
        },
        "hash": {
            "url": "$url.sha256",
            "regex": "$sha256"
        }
    }
}
