{
    "version": "12.16.1",
    "description": "Complete API development environment.",
    "homepage": "https://www.getpostman.com/",
    "license": {
        "identifier": "Freeware",
        "url": "https://www.getpostman.com/licenses/postman_eula"
    },
    "architecture": {
        "64bit": {
            "url": "https://dl.pstmn.io/download/12.16.1/Postman-x64-12.16.1-full.nupkg",
            "hash": "sha1:f75e7d1b5f98578b889e2b8d88878ecdde03bc7a"
        }
    },
    "extract_dir": "lib\\net45",
    "shortcuts": [
        [
            "Postman.exe",
            "Postman"
        ]
    ],
    "checkver": {
        "url": "https://dl.pstmn.io/changelog?channel=stable&platform=win64",
        "jsonpath": "$.changelog[0].name"
    },
    "autoupdate": {
        "architecture": {
            "64bit": {
                "url": "https://dl.pstmn.io/download/$version/Postman-x64-$version-full.nupkg",
                "hash": {
                    "url": "https://dl.pstmn.io/RELEASES?platform=win64&from=$version",
                    "regex": "(?sm)$basename.*?$sha1"
                }
            }
        }
    }
}
